predictram_parameter_data/__init__.py
predictram_parameter_data/api.py
predictram_parameter_data/data_handler.py
predictram_parameter_data/query_parser.py
predictram_parameter_data/visualization.py
predictram_parameter_data/data/all_stocks.json
predictram_parameter_data-0.1.1.dist-info/METADATA
predictram_parameter_data-0.1.1.dist-info/WHEEL
predictram_parameter_data-0.1.1.dist-info/top_level.txt
predictram_parameter_data-0.1.1.dist-info/RECORD
