Metadata-Version: 2.1
Name: predictram_parameter_data
Version: 0.1.1
Summary: A package for querying and analyzing stock parameter data
Home-page: https://github.com/yourusername/predictram-parameter-data
Author: PredictRAM
Author-email: support@predictram.com
Classifier: Programming Language :: Python :: 3
Classifier: License :: OSI Approved :: MIT License
Classifier: Operating System :: OS Independent
Requires-Python: >=3.6
Requires-Dist: pandas >=1.0.0
Requires-Dist: matplotlib >=3.0.0
Requires-Dist: seaborn >=0.10.0
Requires-Dist: openpyxl >=3.0.0
